cgrlib
