Metadata-Version: 1.0
Name: cgrlib
Version: 0.1.1
Summary: Capture waveforms with the CGR-101 USB oscilloscope
Home-page: https://github.com/johnpeck/cgr-capture
Author: John Peck
Author-email: john@johnpeck.info
License: LICENSE.txt
Keywords: testing,logging,example
Platform: UNKNOWN
